eco_parser/__init__.py
eco_parser/__main__.py
eco_parser/cli.py
eco_parser/core.py
eco_parser/element_parsers.py
eco_parser/parser.py
eco_parser-0.3.0.dist-info/LICENSE
eco_parser-0.3.0.dist-info/METADATA
eco_parser-0.3.0.dist-info/WHEEL
eco_parser-0.3.0.dist-info/entry_points.txt
eco_parser-0.3.0.dist-info/top_level.txt
eco_parser-0.3.0.dist-info/RECORD
