Metadata-Version: 2.1
Name: eco_parser
Version: 0.3.0
Summary: Parse ward lists from Electoral Change Orders on http://www.legislation.gov.uk/
Home-page: https://github.com/DemocracyClub/eco-parser/
Author: chris48s
License: MIT
Classifier: License :: OSI Approved :: MIT License
Classifier: Programming Language :: Python
Classifier: Programming Language :: Python :: 3
Classifier: Programming Language :: Python :: 3.10
Classifier: Programming Language :: Python :: 3.11
Classifier: Programming Language :: Python :: 3.12
License-File: LICENSE
Requires-Dist: lxml
Requires-Dist: requests
Provides-Extra: testing
Requires-Dist: coveralls; extra == "testing"
Provides-Extra: development
Requires-Dist: ruff==0.3.7; extra == "development"
